{
  "hints": [],
  "groups": [
    {
      "sourceType": "com.javanewb.common.redis.mybatis.MybatisRedisConfig",
      "name": "spring.redis",
      "type": "com.javanewb.common.redis.mybatis.MybatisRedisConfig"
    }
  ],
  "properties": [
    {
      "sourceType": "com.javanewb.common.redis.mybatis.MybatisRedisConfig",
      "name": "spring.redis.block-when-exhausted",
      "type": "java.lang.Boolean"
    },
    {
      "sourceType": "com.javanewb.common.redis.mybatis.MybatisRedisConfig",
      "name": "spring.redis.client-name",
      "type": "java.lang.String"
    },
    {
      "sourceType": "com.javanewb.common.redis.mybatis.MybatisRedisConfig",
      "defaultValue": 2000,
      "name": "spring.redis.connection-timeout",
      "type": "java.lang.Integer"
    },
    {
      "sourceType": "com.javanewb.common.redis.mybatis.MybatisRedisConfig",
      "defaultValue": 0,
      "name": "spring.redis.database",
      "type": "java.lang.Integer"
    },
    {
      "sourceType": "com.javanewb.common.redis.mybatis.MybatisRedisConfig",
      "name": "spring.redis.eviction-policy-class-name",
      "type": "java.lang.String"
    },
    {
      "sourceType": "com.javanewb.common.redis.mybatis.MybatisRedisConfig",
      "name": "spring.redis.fairness",
      "type": "java.lang.Boolean"
    },
    {
      "sourceType": "com.javanewb.common.redis.mybatis.MybatisRedisConfig",
      "defaultValue": "localhost",
      "name": "spring.redis.host",
      "type": "java.lang.String"
    },
    {
      "sourceType": "com.javanewb.common.redis.mybatis.MybatisRedisConfig",
      "name": "spring.redis.jmx-enabled",
      "type": "java.lang.Boolean"
    },
    {
      "sourceType": "com.javanewb.common.redis.mybatis.MybatisRedisConfig",
      "name": "spring.redis.jmx-name-base",
      "type": "java.lang.String"
    },
    {
      "sourceType": "com.javanewb.common.redis.mybatis.MybatisRedisConfig",
      "name": "spring.redis.jmx-name-prefix",
      "type": "java.lang.String"
    },
    {
      "sourceType": "com.javanewb.common.redis.mybatis.MybatisRedisConfig",
      "name": "spring.redis.lifo",
      "type": "java.lang.Boolean"
    },
    {
      "sourceType": "com.javanewb.common.redis.mybatis.MybatisRedisConfig",
      "name": "spring.redis.max-idle",
      "type": "java.lang.Integer"
    },
    {
      "sourceType": "com.javanewb.common.redis.mybatis.MybatisRedisConfig",
      "name": "spring.redis.max-total",
      "type": "java.lang.Integer"
    },
    {
      "sourceType": "com.javanewb.common.redis.mybatis.MybatisRedisConfig",
      "name": "spring.redis.max-wait-millis",
      "type": "java.lang.Long"
    },
    {
      "sourceType": "com.javanewb.common.redis.mybatis.MybatisRedisConfig",
      "name": "spring.redis.min-evictable-idle-time-millis",
      "type": "java.lang.Long"
    },
    {
      "sourceType": "com.javanewb.common.redis.mybatis.MybatisRedisConfig",
      "name": "spring.redis.min-idle",
      "type": "java.lang.Integer"
    },
    {
      "sourceType": "com.javanewb.common.redis.mybatis.MybatisRedisConfig",
      "name": "spring.redis.num-tests-per-eviction-run",
      "type": "java.lang.Integer"
    },
    {
      "sourceType": "com.javanewb.common.redis.mybatis.MybatisRedisConfig",
      "name": "spring.redis.password",
      "type": "java.lang.String"
    },
    {
      "sourceType": "com.javanewb.common.redis.mybatis.MybatisRedisConfig",
      "defaultValue": 6379,
      "name": "spring.redis.port",
      "type": "java.lang.Integer"
    },
    {
      "sourceType": "com.javanewb.common.redis.mybatis.MybatisRedisConfig",
      "defaultValue": 2000,
      "name": "spring.redis.so-timeout",
      "type": "java.lang.Integer"
    },
    {
      "sourceType": "com.javanewb.common.redis.mybatis.MybatisRedisConfig",
      "name": "spring.redis.soft-min-evictable-idle-time-millis",
      "type": "java.lang.Long"
    },
    {
      "sourceType": "com.javanewb.common.redis.mybatis.MybatisRedisConfig",
      "name": "spring.redis.test-on-borrow",
      "type": "java.lang.Boolean"
    },
    {
      "sourceType": "com.javanewb.common.redis.mybatis.MybatisRedisConfig",
      "name": "spring.redis.test-on-create",
      "type": "java.lang.Boolean"
    },
    {
      "sourceType": "com.javanewb.common.redis.mybatis.MybatisRedisConfig",
      "name": "spring.redis.test-on-return",
      "type": "java.lang.Boolean"
    },
    {
      "sourceType": "com.javanewb.common.redis.mybatis.MybatisRedisConfig",
      "name": "spring.redis.test-while-idle",
      "type": "java.lang.Boolean"
    },
    {
      "sourceType": "com.javanewb.common.redis.mybatis.MybatisRedisConfig",
      "name": "spring.redis.time-between-eviction-runs-millis",
      "type": "java.lang.Long"
    }
  ]
}